pynimomodem/__init__.py
pynimomodem/atcommandbuffer.py
pynimomodem/constants.py
pynimomodem/crcxmodem.py
pynimomodem/location.py
pynimomodem/message.py
pynimomodem/modem.py
pynimomodem/nimoutils.py
pynimomodem/s_registers.py
pynimomodem-0.4.16.dist-info/LICENSE
pynimomodem-0.4.16.dist-info/WHEEL
pynimomodem-0.4.16.dist-info/METADATA
pynimomodem-0.4.16.dist-info/RECORD
