Metadata-Version: 2.1
Name: pynimomodem
Version: 0.4.16
Summary: A Python implementation of Viasat's NIMO modem interface project.
Home-page: https://github.com/inmarsat-enterprise/pynimomodem
License: Apache2.0
Keywords: viasat,inmarsat,satellite,iot,idp,ogx,orbcomm
Author: geoffbrucepayne
Author-email: geoff.bruce-payne@inmarsat.com
Requires-Python: >=3.9,<4.0
Classifier: License :: Other/Proprietary License
Classifier: Programming Language :: Python :: 3
Classifier: Programming Language :: Python :: 3.10
Classifier: Programming Language :: Python :: 3.9
Requires-Dist: pyserial (>=3.5,<4.0)
Project-URL: Repository, https://github.com/inmarsat-enterprise/pynimomodem
